MANIFEST.in
requirements.txt
setup.py
tessera/__init__.py
tessera/_version.py
tessera/application.py
tessera/config.py
tessera/database.py
tessera/helpers.py
tessera/main.py
tessera/tessera.db
tessera/views_api.py
tessera/views_ui.py
tessera.egg-info/PKG-INFO
tessera.egg-info/SOURCES.txt
tessera.egg-info/dependency_links.txt
tessera.egg-info/entry_points.txt
tessera.egg-info/requires.txt
tessera.egg-info/top_level.txt
tessera/client/__init__.py
tessera/client/api/__init__.py
tessera/client/api/client.py
tessera/client/api/model.py
tessera/importer/__init__.py
tessera/importer/graphite.py
tessera/importer/json_importer.py
tessera/static/bundle.js
tessera/static/tessera-typography.css
tessera/static/tessera-typography.css.map
tessera/static/tessera.css
tessera/static/tessera.css.map
tessera/static/tessera.js
tessera/static/css/bundle.css
tessera/static/css/select2-spinner.gif
tessera/static/css/select2.png
tessera/static/fonts/FontAwesome.otf
tessera/static/fonts/fontawesome-webfont.eot
tessera/static/fonts/fontawesome-webfont.svg
tessera/static/fonts/fontawesome-webfont.ttf
tessera/static/fonts/fontawesome-webfont.woff
tessera/static/fonts/glyphicons-halflings-regular.eot
tessera/static/fonts/glyphicons-halflings-regular.svg
tessera/static/fonts/glyphicons-halflings-regular.ttf
tessera/static/fonts/glyphicons-halflings-regular.woff
tessera/static/img/back_disabled.png
tessera/static/img/back_enabled.png
tessera/static/img/back_enabled_hover.png
tessera/static/img/clear.png
tessera/static/img/forward_disabled.png
tessera/static/img/forward_enabled.png
tessera/static/img/forward_enabled_hover.png
tessera/static/img/loading.gif
tessera/static/img/sort_asc.png
tessera/static/img/sort_asc_disabled.png
tessera/static/img/sort_both.png
tessera/static/img/sort_desc.png
tessera/static/img/sort_desc_disabled.png
tessera/static/themes/bootstrap-dark.css
tessera/static/themes/bootstrap-dark.css.map
tessera/static/themes/bootstrap-light.css
tessera/static/themes/bootstrap-light.css.map
tessera/static/themes/bootstrap-snow.css
tessera/static/themes/bootstrap-snow.css.map
tessera/static/themes/bootstrap-solarized-dark.css
