Metadata-Version: 1.1
Name: tessera
Version: 0.10.0
Summary: A dashboard front end for Graphite
Home-page: https://github.com/tessera-metrics/tessera
Author: Adam Alpern
Author-email: UNKNOWN
License: Apache
Platform: UNKNOWN
Classifier: Development Status :: 3 - Alpha
Classifier: Environment :: No Input/Output (Daemon)
Classifier: Framework :: Flask
Classifier: Intended Audience :: Developers
Classifier: Intended Audience :: Information Technology
Classifier: Intended Audience :: System Administrators
Classifier: License :: OSI Approved :: Apache Software License
Classifier: Operating System :: MacOS :: MacOS X
Classifier: Operating System :: POSIX
Classifier: Operating System :: Unix
Classifier: Programming Language :: Python :: 2.7
Classifier: Programming Language :: Python :: 3.5
Classifier: Programming Language :: Python
Classifier: Topic :: System :: Monitoring
Classifier: Topic :: System :: Systems Administration
